total_connect_client/__init__.py
total_connect_client/__main__.py
total_connect_client/client.py
total_connect_client/const.py
total_connect_client/device.py
total_connect_client/exceptions.py
total_connect_client/location.py
total_connect_client/partition.py
total_connect_client/user.py
total_connect_client/zone.py
total_connect_client/live/arm.py
total_connect_client/live/bypass.py
total_connect_client/live/disarm.py
total_connect_client/live/experimental.py
total_connect_client/live/sleepy.py
total_connect_client/live/trigger.py
total_connect_client-2025.12.2.dist-info/licenses/LICENSE
total_connect_client-2025.12.2.dist-info/METADATA
total_connect_client-2025.12.2.dist-info/WHEEL
total_connect_client-2025.12.2.dist-info/top_level.txt
total_connect_client-2025.12.2.dist-info/RECORD
