Metadata-Version: 2.4
Name: total_connect_client
Version: 2025.12.2
Summary: Interact with Total Connect 2 alarm systems
Author-email: "Craig J. Midwinter" <craig.j.midwinter@gmail.com>
License: MIT
Project-URL: Homepage, https://github.com/craigjmidwinter/total-connect-client
Project-URL: Bug Tracker, https://github.com/craigjmidwinter/total-connect-client/issues
Keywords: alarm,TotalConnect
Classifier: Development Status :: 5 - Production/Stable
Classifier: Intended Audience :: Developers
Classifier: Programming Language :: Python :: 3
Classifier: Programming Language :: Python :: 3.10
Classifier: Programming Language :: Python :: 3.11
Classifier: Programming Language :: Python :: 3.12
Classifier: Programming Language :: Python :: 3.13
Classifier: License :: OSI Approved :: MIT License
Classifier: Operating System :: OS Independent
Classifier: Topic :: Home Automation
Classifier: Topic :: Security
Requires-Python: >=3.10
License-File: LICENSE
Requires-Dist: pycryptodome>=3.23.0
Requires-Dist: requests-oauthlib>=2.0.0
Dynamic: license-file
